{"name":"Agregar producto al carrito","id":"automatizar-proceso-de-compra-en-aliexpress;agregar-producto-al-carrito","testSteps":[{"number":1,"description":"1: Agregar producto al carrito ({url\u003d, busqueda\u003d, producto\u003d, precio\u003d})","duration":165,"startTime":"2025-04-24T14:53:50.040286200-05:00[America/Bogota]","result":"IGNORED","precondition":false,"level":0,"lineNumber":24,"children":[{"number":2,"description":"Dado Que me encuentro en la página \u0027\u0027","duration":21,"startTime":"2025-04-24T14:53:50.120296200-05:00[America/Bogota]","result":"PENDING","precondition":false,"level":1},{"number":3,"description":"Cuando busco el producto \u0027\u0027","duration":10,"startTime":"2025-04-24T14:53:50.150292800-05:00[America/Bogota]","result":"IGNORED","precondition":false,"level":1},{"number":4,"description":"Y escojo el producto \u0027\u0027","duration":4,"startTime":"2025-04-24T14:53:50.162294-05:00[America/Bogota]","result":"IGNORED","precondition":false,"level":1},{"number":5,"description":"Entonces verifico el precio \u0027\u0027","duration":7,"startTime":"2025-04-24T14:53:50.169293900-05:00[America/Bogota]","result":"IGNORED","precondition":false,"level":1},{"number":6,"description":"Y añado al carrito","duration":5,"startTime":"2025-04-24T14:53:50.181298400-05:00[America/Bogota]","result":"IGNORED","precondition":false,"level":1},{"number":7,"description":"Entonces visualizo el producto \u0027\u0027 con el precio \u0027\u0027","duration":5,"startTime":"2025-04-24T14:53:50.190297900-05:00[America/Bogota]","result":"IGNORED","precondition":false,"level":1}]}],"userStory":{"id":"automatizar-proceso-de-compra-en-aliexpress","storyName":"Automatizar proceso de compra en aliexpress","displayName":"Automatizar proceso de compra en aliexpress","path":"realizarCompra.feature","type":"feature","qualifiedTag":{"name":"Automatizar proceso de compra en aliexpress","type":"feature","displayName":"Automatizar proceso de compra en aliexpress"}},"featureTag":{"name":"Automatizar proceso de compra en aliexpress","type":"feature","displayName":"Automatizar proceso de compra en aliexpress"},"title":"Agregar producto al carrito","description":"","tags":[{"name":"SmokeTest","type":"tag","displayName":"SmokeTest"},{"name":"Windows","type":"context","displayName":"Windows"},{"name":"Automatizar proceso de compra en aliexpress","type":"feature","displayName":"Automatizar proceso de compra en aliexpress"}],"allTags":[{"name":"SmokeTest","type":"tag","displayName":"SmokeTest"},{"name":"Windows","type":"context","displayName":"Windows"},{"name":"Automatizar proceso de compra en aliexpress","type":"feature","displayName":"Automatizar proceso de compra en aliexpress"}],"startTime":"2025-04-24T14:53:49.702180700-05:00[America/Bogota]","duration":513,"projectKey":"","annotatedResult":"PENDING","isManualTestingUpToDate":false,"context":"windows","dataTable":{"headers":["url","busqueda","producto","precio"],"rows":[{"values":["","","",""],"lineNumber":24,"result":"PENDING"}],"predefinedRows":true,"scenarioOutline":"Dado Que me encuentro en la página \u0027\u003curl\u003e\u0027\n\rCuando busco el producto \u0027\u003cbusqueda\u003e\u0027\n\rY escojo el producto \u0027\u003cproducto\u003e\u0027\n\rEntonces verifico el precio \u0027\u003cprecio\u003e\u0027\n\rY añado al carrito\n\rEntonces visualizo el producto \u0027\u003cproducto\u003e\u0027 con el precio \u0027\u003cprecio\u003e\u0027\n\r","dataSetDescriptors":[{"startRow":0,"rowCount":0,"name":"","description":""}]},"manual":false,"testSource":"Cucumber","result":"PENDING","scenarioOutline":"Dado Que me encuentro en la página \u0027\u003curl\u003e\u0027\r\nCuando busco el producto \u0027\u003cbusqueda\u003e\u0027\r\nY escojo el producto \u0027\u003cproducto\u003e\u0027\r\nEntonces verifico el precio \u0027\u003cprecio\u003e\u0027\r\nY añado al carrito\r\nEntonces visualizo el producto \u0027\u003cproducto\u003e\u0027 con el precio \u0027\u003cprecio\u003e\u0027"}